cqpy/__init__.py
cqpy/_callback.py
cqpy/cqp.py
cqpy/events.py
cqpy/log.py
cqpy/tutorial.py
cqpy/types.py
CQPy-0.1.2.dist-info/LICENSE
CQPy-0.1.2.dist-info/METADATA
CQPy-0.1.2.dist-info/WHEEL
CQPy-0.1.2.dist-info/top_level.txt
CQPy-0.1.2.dist-info/RECORD
