Metadata-Version: 2.1
Name: CQPy
Version: 0.1.2
Summary: CQPy is lightweight CoolQ Python SDK for Python 3.7+
Home-page: UNKNOWN
Author: weak_ptr
Author-email: weak_ptr@outlook.com
License: UNKNOWN
Platform: UNKNOWN
